myanova/__init__.py
myanova/nova.py
myanova-0.1.0.dist-info/METADATA
myanova-0.1.0.dist-info/WHEEL
myanova-0.1.0.dist-info/top_level.txt
myanova-0.1.0.dist-info/RECORD
